enedisgatewaypy/__init__.py
enedisgatewaypy/auth.py
enedisgatewaypy/enedisgateway.py
enedisgatewaypy/exceptions.py
enedisgatewaypy-1.3.dist-info/LICENSE
enedisgatewaypy-1.3.dist-info/METADATA
enedisgatewaypy-1.3.dist-info/WHEEL
enedisgatewaypy-1.3.dist-info/top_level.txt
enedisgatewaypy-1.3.dist-info/RECORD
