Metadata-Version: 2.1
Name: enedisgatewaypy
Version: 1.3
Summary: Fetch Linky data from enedisgateway.tech
Home-page: https://github.com/cyr-ius/enedisgatewaypy/tree/master/enedisgatewaypy
Author: cyr-ius
Author-email: cyr-ius@ipocus.net
License: GPL-3
Keywords: enedis linky async
Classifier: Programming Language :: Python
Classifier: Development Status :: 5 - Production/Stable
Classifier: License :: OSI Approved :: GNU General Public License v3 or later (GPLv3+)
Classifier: Programming Language :: Python :: 3
Classifier: Programming Language :: Python :: 3.5
Classifier: Programming Language :: Python :: 3.6
Classifier: Programming Language :: Python :: 3.7
Classifier: Framework :: AsyncIO
Classifier: Intended Audience :: Developers
Classifier: Intended Audience :: System Administrators
Classifier: Topic :: Home Automation
License-File: LICENSE
